dopesorting/__init__.py
dopesorting/bubble_sort.py
dopesorting/insertion_sort.py
dopesorting/quick_sort.py
dopesorting/selection_sort.py
sorting/__init__.py
sorting/bubble_sort.py
sorting/insertion_sort.py
sorting/quick_sort.py
sorting/selection_sort.py
dopesorting-0.1.dist-info/METADATA
dopesorting-0.1.dist-info/WHEEL
dopesorting-0.1.dist-info/top_level.txt
dopesorting-0.1.dist-info/RECORD
